chrome_fingerprints/__init__.py
chrome_fingerprints/fingerprint_typing.py
chrome_fingerprints/fingerprints.json.xz
chrome_fingerprints/fingerprints.py
chrome_fingerprints/vars.py
chrome_fingerprints-1.1.dist-info/LICENSE
chrome_fingerprints-1.1.dist-info/METADATA
chrome_fingerprints-1.1.dist-info/WHEEL
chrome_fingerprints-1.1.dist-info/top_level.txt
chrome_fingerprints-1.1.dist-info/RECORD
