Metadata-Version: 2.1
Name: chrome-fingerprints
Version: 1.1
Summary: A Collection of 10.000 self-collected Chrome Fingerprints. Wrapped in a easy-to-use API, available as a Compressed or Full-Size Json.
Home-page: https://github.com/Vinyzu/chrome-fingerprints
Author: Vinyzu
License: GNU General Public License v3.0
Keywords: botright,playwright,browser,automation,fingerprints,fingerprinting,dataset,data
Classifier: Topic :: Scientific/Engineering
Classifier: Topic :: Scientific/Engineering :: Artificial Intelligence
Classifier: Topic :: Software Development
Classifier: Topic :: Software Development :: Libraries
Classifier: Topic :: Software Development :: Libraries :: Python Modules
Classifier: Topic :: Internet :: WWW/HTTP :: Browsers
Classifier: License :: OSI Approved :: Apache Software License
Classifier: Programming Language :: Python :: 3
Requires-Python: >=3.8
License-File: LICENSE
Requires-Dist: orjson
Requires-Dist: dacite
Requires-Dist: aiomisc
Provides-Extra: testing
Requires-Dist: pytest ; extra == 'testing'
Requires-Dist: mypy ; extra == 'testing'
Requires-Dist: flake8 ; extra == 'testing'
Requires-Dist: tox ; extra == 'testing'
